ensuro_analytics/__init__.py
ensuro_analytics/__main__.py
ensuro_analytics/analytics/__init__.py
ensuro_analytics/analytics/base.py
ensuro_analytics/analytics/dataframe.py
ensuro_analytics/analytics/review.py
ensuro_analytics/analytics/time_series.py
ensuro_analytics/analytics/etokens/__init__.py
ensuro_analytics/analytics/etokens/alpha.py
ensuro_analytics/analytics/etokens/base.py
ensuro_analytics/analytics/etokens/beta.py
ensuro_analytics/analytics/etokens/dollar_weighted_return.py
ensuro_analytics/analytics/etokens/information.py
ensuro_analytics/analytics/etokens/sharpe.py
ensuro_analytics/analytics/etokens/sortino.py
ensuro_analytics/analytics/etokens/temporal_weighted_return.py
ensuro_analytics/analytics/etokens/time_series.py
ensuro_analytics/analytics/etokens/treynor.py
ensuro_analytics/analytics/etokens/viz_setup.py
ensuro_analytics/analytics/forecast/__init__.py
ensuro_analytics/analytics/forecast/base.py
ensuro_analytics/analytics/forecast/loss_ratio.py
ensuro_analytics/analytics/portfolio/__init__.py
ensuro_analytics/analytics/portfolio/active_policies.py
ensuro_analytics/analytics/portfolio/active_premium.py
ensuro_analytics/analytics/portfolio/base.py
ensuro_analytics/analytics/portfolio/collected_premium.py
ensuro_analytics/analytics/portfolio/default_percentage.py
ensuro_analytics/analytics/portfolio/exposure.py
ensuro_analytics/analytics/portfolio/junior_scr.py
ensuro_analytics/analytics/portfolio/loss_ratio.py
ensuro_analytics/analytics/portfolio/loss_to_exposure.py
ensuro_analytics/analytics/portfolio/n_payouts.py
ensuro_analytics/analytics/portfolio/payouts.py
ensuro_analytics/analytics/portfolio/post_mortem_premium.py
ensuro_analytics/analytics/portfolio/premium_balance.py
ensuro_analytics/analytics/portfolio/scr.py
ensuro_analytics/analytics/portfolio/senior_scr.py
ensuro_analytics/analytics/portfolio/total_policies.py
ensuro_analytics/analytics/portfolio/var.py
ensuro_analytics/download/__init__.py
ensuro_analytics/download/api.py
ensuro_analytics-0.1.14.dist-info/licenses/LICENSE
ensuro_analytics-0.1.14.dist-info/METADATA
ensuro_analytics-0.1.14.dist-info/WHEEL
ensuro_analytics-0.1.14.dist-info/top_level.txt
ensuro_analytics-0.1.14.dist-info/RECORD
